df_websockets/__init__.py
df_websockets/apps.py
df_websockets/celery.py
df_websockets/checks.py
df_websockets/constants.py
df_websockets/consumers.py
df_websockets/decorators.py
df_websockets/load.py
df_websockets/management/__init__.py
df_websockets/management/commands/__init__.py
df_websockets/management/commands/celery.py
df_websockets/management/commands/worker.py
df_websockets/middleware.py
df_websockets/routing.py
df_websockets/static/js/df_websockets.min.js
df_websockets/static/js/df_websockets.min.js.map
df_websockets/tasks.py
df_websockets/templatetags/__init__.py
df_websockets/templatetags/websockets.py
df_websockets/testing.py
df_websockets/topics.py
df_websockets/utils.py
df_websockets/window_info.py
df_websockets/ws_middleware.py
df_websockets/ws_settings.py
df_websockets-1.2.5.dist-info/LICENSE
df_websockets-1.2.5.dist-info/METADATA
df_websockets-1.2.5.dist-info/WHEEL
df_websockets-1.2.5.dist-info/RECORD
